number_counter/__init__.py
number_counter/counter.py
number_counter-0.2.1.dist-info/LICENSE
number_counter-0.2.1.dist-info/METADATA
number_counter-0.2.1.dist-info/WHEEL
number_counter-0.2.1.dist-info/top_level.txt
number_counter-0.2.1.dist-info/RECORD
